README.md
setup.cfg
setup.py
bin/snaptools
snaptools/__init__.py
snaptools/add_bmat.py
snaptools/add_gmat.py
snaptools/add_pmat.py
snaptools/alignment.py
snaptools/call_peak.py
snaptools/dump_barcode.py
snaptools/fastq_dex.py
snaptools/global_var.py
snaptools/gtf.py
snaptools/louvain.py
snaptools/parser.py
snaptools/snap.py
snaptools/snap_pre.py
snaptools/utilities.py
snaptools.egg-info/PKG-INFO
snaptools.egg-info/SOURCES.txt
snaptools.egg-info/dependency_links.txt
snaptools.egg-info/not-zip-safe
snaptools.egg-info/requires.txt
snaptools.egg-info/top_level.txt